[{"city":"\u81fa\u5317","active_student_cnt":8804,"city_total_student_cnt":337169,"active_ratio":0.0261115346},{"city":"\u65b0\u5317","active_student_cnt":7444,"city_total_student_cnt":466142,"active_ratio":0.0159693827},{"city":"\u81fa\u4e2d","active_student_cnt":6104,"city_total_student_cnt":409171,"active_ratio":0.0149179683},{"city":"\u9ad8\u96c4","active_student_cnt":3588,"city_total_student_cnt":339869,"active_ratio":0.0105570087},{"city":"\u6843\u5712","active_student_cnt":2590,"city_total_student_cnt":312521,"active_ratio":0.0082874431},{"city":"\u81fa\u5357","active_student_cnt":1988,"city_total_student_cnt":240567,"active_ratio":0.0082638101},{"city":"\u5b9c\u862d","active_student_cnt":1674,"city_total_student_cnt":59904,"active_ratio":0.0279447115},{"city":"\u5c4f\u6771","active_student_cnt":1502,"city_total_student_cnt":96113,"active_ratio":0.0156274385},{"city":"\u65b0\u7af9","active_student_cnt":1147,"city_total_student_cnt":157396,"active_ratio":0.0072873516},{"city":"\u5f70\u5316","active_student_cnt":1119,"city_total_student_cnt":166501,"active_ratio":0.0067206804},{"city":"\u96f2\u6797","active_student_cnt":904,"city_total_student_cnt":88663,"active_ratio":0.0101959104},{"city":"\u82d7\u6817","active_student_cnt":862,"city_total_student_cnt":72479,"active_ratio":0.0118931001},{"city":"\u5357\u6295","active_student_cnt":801,"city_total_student_cnt":63395,"active_ratio":0.0126350659},{"city":"\u81fa\u6771","active_student_cnt":615,"city_total_student_cnt":27797,"active_ratio":0.0221246897},{"city":"\u5609\u7fa9","active_student_cnt":481,"city_total_student_cnt":100005,"active_ratio":0.0048097595},{"city":"\u82b1\u84ee","active_student_cnt":347,"city_total_student_cnt":43473,"active_ratio":0.0079819658},{"city":"\u91d1\u9580","active_student_cnt":264,"city_total_student_cnt":9602,"active_ratio":0.027494272},{"city":"\u57fa\u9686","active_student_cnt":219,"city_total_student_cnt":45244,"active_ratio":0.0048404208},{"city":"\u6f8e\u6e56","active_student_cnt":155,"city_total_student_cnt":10561,"active_ratio":0.0146766405},{"city":"\u9023\u6c5f","active_student_cnt":49,"city_total_student_cnt":1320,"active_ratio":0.0371212121}]